{"sections":{"main":{"type":"main-page","blocks":{"heading":{"type":"text","name":"Title","disabled":true,"settings":{"text":"<h1>{{ closest.page.title }}<\/h1>","width":"100%","max_width":"normal","alignment":"left","type_preset":"h2","font":"var(--font-body--family)","font_size":"1rem","line_height":"normal","letter_spacing":"normal","case":"none","wrap":"pretty","color":"var(--color-foreground)","background":false,"background_color":"#00000026","corner_radius":0,"padding-block-start":0,"padding-block-end":0,"padding-inline-start":0,"padding-inline-end":0},"blocks":{}},"page-content":{"type":"page-content","disabled":true,"settings":{},"blocks":{}}},"block_order":["heading","page-content"],"settings":{"content_direction":"column","gap":32,"color_scheme":"","padding-block-start":40,"padding-block-end":80}},"hero_mrUiJU":{"type":"hero","blocks":{"text_ADqhMJ":{"type":"text","settings":{"text":"<h1>Care guide<\/h1>","width":"fit-content","max_width":"narrow","alignment":"left","type_preset":"h1","font":"var(--font-body--family)","font_size":"1rem","line_height":"normal","letter_spacing":"normal","case":"none","wrap":"pretty","color":"var(--color-foreground)","background":false,"background_color":"#00000026","corner_radius":0,"padding-block-start":0,"padding-block-end":0,"padding-inline-start":0,"padding-inline-end":0},"blocks":{}},"text_pPUKKK":{"type":"text","settings":{"text":"<p>Made with care and unconditionally loved by our customers.<\/p>","width":"fit-content","max_width":"narrow","alignment":"left","type_preset":"rte","font":"var(--font-body--family)","font_size":"1rem","line_height":"normal","letter_spacing":"normal","case":"none","wrap":"pretty","color":"var(--color-foreground)","background":false,"background_color":"#00000026","corner_radius":0,"padding-block-start":0,"padding-block-end":32,"padding-inline-start":0,"padding-inline-end":0},"blocks":{}},"button_KbCkjM":{"type":"button","name":"t:names.button","settings":{"label":"Shop Now","link":"shopify:\/\/collections\/all","open_in_new_tab":false,"style_class":"button","width":"fit-content","custom_width":100,"width_mobile":"fit-content","custom_width_mobile":100},"blocks":{}}},"block_order":["text_ADqhMJ","text_pPUKKK","button_KbCkjM"],"name":"t:names.hero","settings":{"media_type_1":"image","image_1":"shopify:\/\/shop_images\/A7R3073-min.jpg","media_type_2":"image","link":"","open_in_new_tab":false,"content_direction":"column","vertical_on_mobile":true,"horizontal_alignment":"flex-start","vertical_alignment":"center","align_baseline":false,"horizontal_alignment_flex_direction_column":"center","vertical_alignment_flex_direction_column":"center","gap":16,"section_width":"page-width","section_height":"large","section_height_custom":50,"color_scheme":"scheme-5","toggle_overlay":true,"overlay_color":"#00000026","overlay_style":"gradient","gradient_direction":"to top","blurred_reflection":false,"reflection_opacity":75,"padding-block-start":40,"padding-block-end":40}},"media_with_content_fEUwyj":{"type":"media-with-content","blocks":{"media":{"type":"_media-without-appearance","static":true,"settings":{"media_type":"image","link":"","video_loop":true,"video_autoplay":false,"image_position":"cover","video_position":"cover"},"blocks":{}},"content":{"type":"_content-without-appearance","static":true,"settings":{"horizontal_alignment_flex_direction_column":"flex-start","vertical_alignment_flex_direction_column":"space-between","gap":24},"blocks":{"text_3LcU6R":{"type":"text","name":"t:names.caption","settings":{"text":"<p>Bestseller<\/p>","width":"fit-content","max_width":"normal","alignment":"left","type_preset":"h6","font":"var(--font-body--family)","font_size":"1rem","line_height":"normal","letter_spacing":"normal","case":"none","wrap":"pretty","color":"var(--color-foreground)","background":false,"background_color":"#00000026","corner_radius":0,"padding-block-start":0,"padding-block-end":0,"padding-inline-start":0,"padding-inline-end":0},"blocks":{}},"group_DTefmV":{"type":"group","settings":{"link":"","open_in_new_tab":false,"content_direction":"column","vertical_on_mobile":true,"horizontal_alignment":"flex-start","vertical_alignment":"center","align_baseline":false,"horizontal_alignment_flex_direction_column":"flex-start","vertical_alignment_flex_direction_column":"center","gap":12,"width":"fill","custom_width":100,"width_mobile":"fill","custom_width_mobile":100,"height":"fit","custom_height":100,"inherit_color_scheme":true,"color_scheme":"","background_media":"none","video_position":"cover","background_image_position":"cover","border":"none","border_width":1,"border_opacity":100,"border_radius":0,"placeholder":"","toggle_overlay":false,"overlay_color":"#00000026","overlay_style":"solid","gradient_direction":"to top","padding-block-start":0,"padding-block-end":0,"padding-inline-start":0,"padding-inline-end":0},"blocks":{"text_7L6ihF":{"type":"text","name":"t:names.heading","settings":{"text":"<h2>Our signature product<\/h2>","width":"fit-content","max_width":"normal","alignment":"left","type_preset":"h3","font":"var(--font-body--family)","font_size":"1rem","line_height":"normal","letter_spacing":"normal","case":"none","wrap":"pretty","color":"var(--color-foreground)","background":false,"background_color":"#00000026","corner_radius":0,"padding-block-start":0,"padding-block-end":0,"padding-inline-start":0,"padding-inline-end":0},"blocks":{}},"text_BmKQTz":{"type":"text","settings":{"text":"<p>Made with care and unconditionally loved by our customers, this signature bestseller exceeds all expectations.<\/p>","width":"fit-content","max_width":"narrow","alignment":"left","type_preset":"rte","font":"var(--font-body--family)","font_size":"1rem","line_height":"normal","letter_spacing":"normal","case":"none","wrap":"pretty","color":"var(--color-foreground)","background":false,"background_color":"#00000026","corner_radius":0,"padding-block-start":0,"padding-block-end":0,"padding-inline-start":0,"padding-inline-end":0},"blocks":{}}},"block_order":["text_7L6ihF","text_BmKQTz"]},"button_Ut3DeG":{"type":"button","settings":{"label":"Shop now","link":"shopify:\/\/collections\/all","open_in_new_tab":false,"style_class":"link","width":"fit-content","custom_width":100,"width_mobile":"fit-content","custom_width_mobile":100},"blocks":{}}},"block_order":["text_3LcU6R","group_DTefmV","button_Ut3DeG"]}},"name":"t:names.editorial","settings":{"media_position":"left","media_width":"medium","media_height":"60svh","section_width":"full-width","extend_media":true,"color_scheme":"scheme-4","padding-block-start":0,"padding-block-end":0}},"divider_JQRLWz":{"type":"divider","name":"t:names.divider_section","settings":{"color_scheme":"","section_width":"full-width","thickness":1,"corner_radius":"square","width_percent":100,"alignment_horizontal":"center","padding-block-start":16,"padding-block-end":16}}},"order":["main","hero_mrUiJU","divider_JQRLWz","media_with_content_fEUwyj"]}